luna/__init__.py
luna/base.py
luna/blanc.py
luna/calculate.py
luna/mover_score.py
luna/ngram.py
luna/pretrained.py
luna/reference_free.py
luna/rouge_we.py
luna/s3.py
luna/sources/__init__.py
luna/sources/bart_score.py
luna/sources/bary_score.py
luna/sources/data_stats_metrics.py
luna/sources/data_stats_utils.py
luna/sources/depth_score.py
luna/sources/info_lm.py
luna/sources/moverscore_utils.py
luna/sources/rouge_we_utils.py
luna/sources/s3_utils/js_utils.py
luna/sources/s3_utils/rouge_n_utils.py
luna/sources/s3_utils/s3_utils.py
luna/sources/summ_eval_metric.py
luna/statistical_measures.py
luna/summaqa.py
luna/utils.py
luna_nlg-1.0.0.dist-info/METADATA
luna_nlg-1.0.0.dist-info/WHEEL
luna_nlg-1.0.0.dist-info/RECORD
