Metadata-Version: 2.1
Name: luna-nlg
Version: 1.0.0
Summary: Source code for the LUNA project
License: MIT
Author: Marat Saidov
Author-email: marat.a.saidov@gmail.com
Requires-Python: >=3.8,<3.11
Classifier: License :: OSI Approved :: MIT License
Classifier: Programming Language :: Python :: 3
Classifier: Programming Language :: Python :: 3.8
Classifier: Programming Language :: Python :: 3.9
Classifier: Programming Language :: Python :: 3.10
Requires-Dist: POT (==0.9.0)
Requires-Dist: absl-py (==1.4.0)
Requires-Dist: bert-score (==0.3.13)
Requires-Dist: blanc (==0.3.0)
Requires-Dist: evaluate (==0.4.0)
Requires-Dist: gdown (==4.7.1)
Requires-Dist: geomloss (==0.2.6)
Requires-Dist: gin-config (==0.5.0)
Requires-Dist: joblib (==1.3.2)
Requires-Dist: numpy (==1.24.1)
Requires-Dist: pyemd (==1.0.0)
Requires-Dist: rouge-score (==0.1.2)
Requires-Dist: sacrebleu (==2.3.1)
Requires-Dist: scikit-learn (==1.2.2)
Requires-Dist: scipy (==1.10.1)
Requires-Dist: six (==1.16.0)
Requires-Dist: spacy (==3.5.2)
Requires-Dist: torch (==1.12.1)
Requires-Dist: transformers (==4.28.1)
